docs/__init__.py
docs/conf.py
docs/docopt.py
tests/__init__.py
tests/test_api.py
tests/core/__init__.py
tests/core/test_topology.py
topology/__init__.py
topology/__main__.py
topology/api.py
topology/cli.py
topology/core/__init__.py
topology/core/constants.py
topology/core/policies.py
topology/core/topology.py
topology/core/utils.py
topology_yaml-0.1.5.dist-info/DESCRIPTION.rst
topology_yaml-0.1.5.dist-info/LICENSE.txt
topology_yaml-0.1.5.dist-info/METADATA
topology_yaml-0.1.5.dist-info/RECORD
topology_yaml-0.1.5.dist-info/WHEEL
topology_yaml-0.1.5.dist-info/entry_points.txt
topology_yaml-0.1.5.dist-info/metadata.json
topology_yaml-0.1.5.dist-info/top_level.txt
